cachemir/__init__.py
cachemir/get_data_in_project_example.py
cachemir/main.py
cachemir/cli/__init__.py
cachemir/cli/example_shell_script.py
cachemir/data/__init__.py
cachemir/data/test_data.csv
cachemir-0.0.1.dist-info/licenses/LICENSE
cachemir-0.0.1.dist-info/METADATA
cachemir-0.0.1.dist-info/WHEEL
cachemir-0.0.1.dist-info/entry_points.txt
cachemir-0.0.1.dist-info/top_level.txt
cachemir-0.0.1.dist-info/RECORD
