Metadata-Version: 2.4
Name: cachemir
Version: 0.0.1
Summary: SHORT DESC.
Author-email: MatteoLacki <matteo.lacki@gmail.com>
Project-URL: homepage, https://github.com/MatteoLacki/cachemir.git
Project-URL: repository, https://github.com/MatteoLacki/cachemir.git
Requires-Python: >=3.6
License-File: LICENSE
Requires-Dist: click
Dynamic: license-file
